QUANTAXIS_CRAWLY/eastmoney_simulation_web_trader.py
QUANTAXIS_CRAWLY/gecko_example.py
QUANTAXIS_CRAWLY/jrj_divyield_simulation_web.py
QUANTAXIS_CRAWLY/jrj_simulation_web.py
QUANTAXIS_CRAWLY/run_crawl.py
QUANTAXIS_CRAWLY/run_selenium_alone.py
QUANTAXIS_CRAWLY-1.0.dist-info/METADATA
QUANTAXIS_CRAWLY-1.0.dist-info/WHEEL
QUANTAXIS_CRAWLY-1.0.dist-info/top_level.txt
QUANTAXIS_CRAWLY-1.0.dist-info/zip-safe
QUANTAXIS_CRAWLY-1.0.dist-info/RECORD
